aqbt/__init__.py
aqbt/__version__.py
aqbt/aquarium/__init__.py
aqbt/aquarium/faker.py
aqbt/aquarium/genome_builder.py
aqbt/aquarium/linter.py
aqbt/aquarium/parsers/data/NORGateParts.csv
aqbt/aquarium/parsers/data/amporibackbone.gb
aqbt/aquarium/parsers/data/wset_conversion.json
aqbt/aquarium/parsers/pgrr_plasmid.py
aqbt/aquarium/parsers/register_all_pgrr.py
aqbt/aquarium/pydent_utils.py
aqbt/aquarium/registry.py
aqbt/aquarium/registry_crawler.py
aqbt/aquarium/resolve_sequences.py
aqbt/aquarium/serializer.py
aqbt/bioadapter/__init__.py
aqbt/bioadapter/_bioadapter.py
aqbt/bioadapter/conversion.py
aqbt/biopython/__init__.py
aqbt/biopython/lint.py
aqbt/build_request/__init__.py
aqbt/build_request/cell_value.py
aqbt/build_request/exceptions.py
aqbt/build_request/parser.py
aqbt/build_request/schema.json
aqbt/build_request/schema.py
aqbt/build_request/validate.py
aqbt/contrib/__init__.py
aqbt/contrib/uwbf/__init__.py
aqbt/contrib/uwbf/primer_utils/__init__.py
aqbt/design/__init__.py
aqbt/design/archived/uwbf_adapter.py
aqbt/design/archived/uwbf_adapter_v2.py
aqbt/design/build_request_parser.py
aqbt/design/components/__init__.py
aqbt/design/components/aq_to_dna_inventory_json.py
aqbt/design/dasi/__init__.py
aqbt/design/dasi/dasi.config.toml
aqbt/design/dasi/dasi_to_aq/convert.py
aqbt/design/dasi/dasi_to_aquarium.py
aqbt/design/dasi/dfs.py
aqbt/design/dasi/terrarium.sh
aqbt/exceptions.py
aqbt/genome.py
aqbt/logger.py
aqbt/schema/README.md
aqbt/schema/__init__.py
aqbt/sequence/__init__.py
aqbt/tools.py
aqbt/utils/__init__.py
aqbt/utils/region.py
aqbt-0.0.2.dist-info/WHEEL
aqbt-0.0.2.dist-info/METADATA
aqbt-0.0.2.dist-info/RECORD
