Metadata-Version: 2.1
Name: aqbt
Version: 0.0.2
Summary: Aquarium strain builder tools
Author: Justin Vrana
Author-email: justin.vrana@gmail.com
Requires-Python: >=3.6.1,<4.0.0
Classifier: Programming Language :: Python :: 3
Classifier: Programming Language :: Python :: 3.7
Classifier: Programming Language :: Python :: 3.8
Classifier: Programming Language :: Python :: 3.9
Requires-Dist: bcbio-gff (>=0.6.6,<0.7.0)
Requires-Dist: benchlingapi (>=2.1.11,<3.0.0)
Requires-Dist: biopython (>=1.78,<2.0)
Requires-Dist: colour (>=0.1.5,<0.2.0)
Requires-Dist: dasi (>=0.2.1,<0.3.0)
Requires-Dist: google-api-python-client (>=1.7,<2.0)
Requires-Dist: google-auth-httplib2 (>=0.0.3,<0.0.4)
Requires-Dist: google-auth-oauthlib (>=0.4.1,<0.5.0)
Requires-Dist: loggable-jdv (>=0.1.7,<0.2.0)
Requires-Dist: networkx (>=2.5,<3.0)
Requires-Dist: primer3plus (>=1.0,<2.0)
Requires-Dist: pyblastbio (>=0.9,<0.10)
Requires-Dist: pydent (>=1.0.6,<2.0.0)
Requires-Dist: toml (>=0.10.0,<0.11.0)
Requires-Dist: tqdm (>=4.36,<5.0)
Requires-Dist: validators (>=0.14.1,<0.15.0)
